Workbook

Sheet Assumptions
A1: RENVOA CLINIC — Model Assumptions
A3: OPERATING ASSUMPTIONS
A5: Monthly orders (Base) | B5: 150 | C5: Orders per month — Year 1 base case
A6: Average units per order | B6: 1.8 | C6: Vials per order
A7: Free shipping threshold ($) | B7: 150 | C7: From website promo
A8: Payment processing rate | B8: 0.029 | C8: Stripe ~2.9%
A9: Payment fixed fee ($) | B9: 0.3 | C9: Per transaction
A10: Return/refund rate | B10: 0.03 | C10: Industry estimate
A11: Marketing % of revenue | B11: 0.25 | C11: DTC peptide e-commerce
A12: Monthly fixed overhead ($) | B12: 1850 | C12: Excl. marketing — see detail
A13: Ramp — Month 1 orders | B13: 40 | C13: Launch month
A14: Ramp — Month 6 orders | B14: 120 | C14: Mid-year
A15: Ramp — Month 12 orders | B15: 200 | C15: End Year 1
A16: Wholesale tier | B16: 100-vial MOQ | C16: Source: Wholesale Peptide Supply
A18: FIXED MONTHLY OVERHEAD DETAIL
A19: E-commerce platform & hosting | B19: 75
A20: Cold storage / fulfillment | B20: 250
A21: Insurance & legal compliance | B21: 300
A22: Accounting & bookkeeping | B22: 150
A23: Customer support (part-time) | B23: 500
A24: Software (email, analytics, COA) | B24: 125
A25: Miscellaneous | B25: 450
A26: Total fixed overhead | B26: =SUM(B19:B25)

Sheet Pricing Analysis
A1: RENVOA CLINIC — Product Pricing & Margin Analysis
A3: Source: Wholesale Peptide Supply published wholesale (100-vial MOQ, Jul 2026); competitor retail from Biotech Peptides, Grey Research (Jul 2026)
A5: Product | B5: Size | C5: RENVOA Price | D5: Wholesale COGS | E5: Packaging/COA | F5: Landed COGS | G5: Gross Profit | H5: Gross Margin % | I5: Competitor Low | J5: Competitor High | K5: vs Market | L5: Verdict
A6: BPC-157 | B6: 5mg | C6: 49 | D6: 16 | E6: 3 | F6: =C6+D6+E6 | G6: =C6-F6 | H6: =G6/C6 | I6: 45 | J6: 52 | K6: =IF(C6<I6,"Below market",IF(C6>J6,"Above market","Competitive")) | L6: =IF(H6>=0.5,"✓ Profitable",IF(H6>=0.35,"Marginal","Review pricing"))
A7: TB-500 | B7: 5mg | C7: 59 | D7: 30 | E7: 3 | F7: =C7+D7+E7 | G7: =C7-F7 | H7: =G7/C7 | I7: 72 | J7: 72 | K7: =IF(C7<I7,"Below market",IF(C7>J7,"Above market","Competitive")) | L7: =IF(H7>=0.5,"✓ Profitable",IF(H7>=0.35,"Marginal","Review pricing"))
A8: Semaglutide | B8: 2mg | C8: 89 | D8: 8 | E8: 4 | F8: =C8+D8+E8 | G8: =C8-F8 | H8: =G8/C8 | I8: 120 | J8: 150 | K8: =IF(C8<I8,"Below market",IF(C8>J8,"Above market","Competitive")) | L8: =IF(H8>=0.5,"✓ Profitable",IF(H8>=0.35,"Marginal","Review pricing"))
A9: Ipamorelin | B9: 2mg | C9: 39 | D9: 10 | E9: 3 | F9: =C9+D9+E9 | G9: =C9-F9 | H9: =G9/C9 | I9: 35 | J9: 50 | K9: =IF(C9<I9,"Below market",IF(C9>J9,"Above market","Competitive")) | L9: =IF(H9>=0.5,"✓ Profitable",IF(H9>=0.35,"Marginal","Review pricing"))
A10: CJC-1295 (no DAC) | B10: 2mg | C10: 45 | D10: 15 | E10: 3 | F10: =C10+D10+E10 | G10: =C10-F10 | H10: =G10/C10 | I10: 40 | J10: 55 | K10: =IF(C10<I10,"Below market",IF(C10>J10,"Above market","Competitive")) | L10: =IF(H10>=0.5,"✓ Profitable",IF(H10>=0.35,"Marginal","Review pricing"))
A11: GHK-Cu | B11: 50mg | C11: 35 | D11: 15 | E11: 2 | F11: =C11+D11+E11 | G11: =C11-F11 | H11: =G11/C11 | I11: 28 | J11: 45 | K11: =IF(C11<I11,"Below market",IF(C11>J11,"Above market","Competitive")) | L11: =IF(H11>=0.5,"✓ Profitable",IF(H11>=0.35,"Marginal","Review pricing"))
A13: WEIGHTED AVERAGE (assumed mix) | C13: =SUMPRODUCT(C6:C11,B16:B21)/SUM(B16:B21) | F13: =SUMPRODUCT(F6:F11,B16:B21)/SUM(B16:B21) | G13: =C13-F13 | H13: =G13/C13
A15: Assumed sales mix (% of units)
A16: BPC-157 | B16: 0.28
A17: TB-500 | B17: 0.18
A18: Semaglutide | B18: 0.15
A19: Ipamorelin | B19: 0.17
A20: CJC-1295 | B20: 0.12
A21: GHK-Cu | B21: 0.1
A22: Total mix | B22: =SUM(B16:B21)
A24: KEY FINDINGS
A25: ✓ All 6 SKUs show 43–78% gross margins at 100-vial wholesale MOQ pricing
A26: ✓ RENVOA prices sit at or below major competitors — competitive positioning
A27: ⚠ TB-500 has thinnest margin (44%) — consider $64–69 or bundle pricing
A28: ✓ Semaglutide 2mg at $89 is strong vs competitors selling 5mg at $120–150
A29: ⚠ Requires ~$1,600 minimum inventory buy-in (100 vials) before first sale
A30: ⚠ Cold-chain shipping ($12–22/order) erodes margin on orders under $150

Sheet Monthly P&L
A1: RENVOA CLINIC — Monthly Profit & Loss (Year 1)
A3: Line Item | B3: Jan | C3: Feb | D3: Mar | E3: Apr | F3: May | G3: Jun | H3: Jul | I3: Aug | J3: Sep | K3: Oct | L3: Nov | M3: Dec | N3: YEAR 1 TOTAL
A4: Orders | B4: 40 | C4: 55 | D4: 70 | E4: 85 | F4: 100 | G4: 120 | H4: 135 | I4: 150 | J4: 165 | K4: 180 | L4: 190 | M4: 200 | N4: =SUM(B4:M4)
A5: Units sold | B5: =B4*Assumptions!$B$6 | C5: =C4*Assumptions!$B$6 | D5: =D4*Assumptions!$B$6 | E5: =E4*Assumptions!$B$6 | F5: =F4*Assumptions!$B$6 | G5: =G4*Assumptions!$B$6 | H5: =H4*Assumptions!$B$6 | I5: =I4*Assumptions!$B$6 | ... M5: =M4*Assumptions!$B$6 | N5: =SUM(B5:M5)
A6: Gross Revenue | B6: =B4*Assumptions!$B$6*'Pricing Analysis'!$C$13 | C6: =C4*Assumptions!$B$6*'Pricing Analysis'!$C$13 | D6: =D4*Assumptions!$B$6*'Pricing Analysis'!$C$13 | E6: =E4*Assumptions!$B$6*'Pricing Analysis'!$C$13 | F6: =F4*Assumptions!$B$6*'Pricing Analysis'!$C$13 | G6: =G4*Assumptions!$B$6*'Pricing Analysis'!$C$13 | H6: =H4*Assumptions!$B$6*'Pricing Analysis'!$C$13 | I6: =I4*Assumptions!$B$6*'Pricing Analysis'!$C$13 | ... M6: =M4*Assumptions!$B$6*'Pricing Analysis'!$C$13 | N6: =SUM(B6:M6)
A7: Less: Refunds | B7: =-B6*Assumptions!$B$9 | C7: =-C6*Assumptions!$B$9 | D7: =-D6*Assumptions!$B$9 | E7: =-E6*Assumptions!$B$9 | F7: =-F6*Assumptions!$B$9 | G7: =-G6*Assumptions!$B$9 | H7: =-H6*Assumptions!$B$9 | I7: =-I6*Assumptions!$B$9 | ... M7: =-M6*Assumptions!$B$9 | N7: =SUM(B7:M7)
A8: Net Revenue | B8: =B6+B7 | C8: =C6+C7 | D8: =D6+D7 | E8: =E6+E7 | F8: =F6+F7 | G8: =G6+G7 | H8: =H6+H7 | I8: =I6+I7 | ... M8: =M6+M7 | N8: =SUM(B8:M8)
A10: COGS — Product | B10: =B5*'Pricing Analysis'!$F$13 | C10: =C5*'Pricing Analysis'!$F$13 | D10: =D5*'Pricing Analysis'!$F$13 | E10: =E5*'Pricing Analysis'!$F$13 | F10: =F5*'Pricing Analysis'!$F$13 | G10: =G5*'Pricing Analysis'!$F$13 | H10: =H5*'Pricing Analysis'!$F$13 | I10: =I5*'Pricing Analysis'!$F$13 | ... M10: =M5*'Pricing Analysis'!$F$13 | N10: =SUM(B10:M10)
A11: COGS — Shipping outbound | B11: =B4*14 | C11: =C4*14 | D11: =D4*14 | E11: =E4*14 | F11: =F4*14 | G11: =G4*14 | H11: =H4*14 | I11: =I4*14 | ... M11: =M4*14 | N11: =SUM(B11:M11)
A12: COGS — Payment processing | B12: =B6*Assumptions!$B$7+B4*Assumptions!$B$8 | C12: =C6*Assumptions!$B$7+C4*Assumptions!$B$8 | D12: =D6*Assumptions!$B$7+D4*Assumptions!$B$8 | E12: =E6*Assumptions!$B$7+E4*Assumptions!$B$8 | F12: =F6*Assumptions!$B$7+F4*Assumptions!$B$8 | G12: =G6*Assumptions!$B$7+G4*Assumptions!$B$8 | H12: =H6*Assumptions!$B$7+H4*Assumptions!$B$8 | I12: =I6*Assumptions!$B$7+I4*Assumptions!$B$8 | ... M12: =M6*Assumptions!$B$7+M4*Assumptions!$B$8 | N12: =SUM(B12:M12)
A13: Total COGS | B13: =B10+B11+B12 | C13: =C10+C11+C12 | D13: =D10+D11+D12 | E13: =E10+E11+E12 | F13: =F10+F11+F12 | G13: =G10+G11+G12 | H13: =H10+H11+H12 | I13: =I10+I11+I12 | ... M13: =M10+M11+M12 | N13: =SUM(B13:M13)
A14: Gross Profit | B14: =B8-B13 | C14: =C8-C13 | D14: =D8-D13 | E14: =E8-E13 | F14: =F8-F13 | G14: =G8-G13 | H14: =H8-H13 | I14: =I8-I13 | ... M14: =M8-M13 | N14: =SUM(B14:M14)
A15: Gross Margin % | B15: =IF(B8=0,"-",B14/B8) | C15: =IF(C8=0,"-",C14/C8) | D15: =IF(D8=0,"-",D14/D8) | E15: =IF(E8=0,"-",E14/E8) | F15: =IF(F8=0,"-",F14/F8) | G15: =IF(G8=0,"-",G14/G8) | H15: =IF(H8=0,"-",H14/H8) | I15: =IF(I8=0,"-",I14/I8) | ... N15: =IF(N8=0,"-",N14/N8)
A17: Operating Expenses
A18: Marketing & ads | B18: =B8*Assumptions!$B$10 | C18: =C8*Assumptions!$B$10 | D18: =D8*Assumptions!$B$10 | E18: =E8*Assumptions!$B$10 | F18: =F8*Assumptions!$B$10 | G18: =G8*Assumptions!$B$10 | H18: =H8*Assumptions!$B$10 | I18: =I8*Assumptions!$B$10 | ... M18: =M8*Assumptions!$B$10 | N18: =SUM(B18:M18)
A19: Fixed overhead | B19: =Assumptions!$B$26 | C19: =Assumptions!$B$26 | D19: =Assumptions!$B$26 | E19: =Assumptions!$B$26 | F19: =Assumptions!$B$26 | G19: =Assumptions!$B$26 | H19: =Assumptions!$B$26 | I19: =Assumptions!$B$26 | ... M19: =Assumptions!$B$26 | N19: =SUM(B19:M19)
A20: Total OpEx | B20: =B18+B19 | C20: =C18+C19 | D20: =D18+D19 | E20: =E18+E19 | F20: =F18+F19 | G20: =G18+G19 | H20: =H18+H19 | I20: =I18+I19 | ... M20: =M18+M19 | N20: =SUM(B20:M20)
A22: EBITDA | B22: =B14-B20 | C22: =C14-C20 | D22: =D14-D20 | E22: =E14-E20 | F22: =F14-F20 | G22: =G14-G20 | H22: =H14-H20 | I22: =I14-I20 | ... M22: =M14-M20 | N22: =SUM(B22:M22)
A23: EBITDA Margin % | B23: =IF(B8=0,"-",B22/B8) | C23: =IF(C8=0,"-",C22/C8) | D23: =IF(D8=0,"-",D22/D8) | E23: =IF(E8=0,"-",E22/E8) | F23: =IF(F8=0,"-",F22/F8) | G23: =IF(G8=0,"-",G22/G8) | H23: =IF(H8=0,"-",H22/H8) | I23: =IF(I8=0,"-",I22/I8) | ... N23: =IF(N8=0,"-",N22/N8)

Sheet Scenarios
A1: RENVOA CLINIC — Scenario Summary (Annual)
A3: Metric | B3: Conservative | C3: Base (Model) | D3: Optimistic
A4: Annual orders | B4: 900 | C4: 1490 | D4: 2400
A5: Avg order value ($) | B5: 93 | C5: 95.8 | D5: 98
A6: Fully-loaded gross margin % | B6: 0.38 | C6: 0.446 | D6: 0.48
A7: Marketing % of revenue | B7: 0.3 | C7: 0.25 | D7: 0.2
A8: Annual fixed overhead ($) | B8: 22200 | C8: 22200 | D8: 24000
A9: Gross Revenue | B9: =B4*B5 | C9: =C4*C5 | D9: =D4*D5
A10: Gross Profit | B10: =B9*B6 | C10: =C9*C6 | D10: =D9*D6
A11: Marketing spend | B11: =B9*B7 | C11: =C9*C7 | D11: =D9*D7
A12: Fixed overhead | B12: =B8 | C12: =C8 | D12: =D8
A13: Total OpEx | B13: =B12+B13 | C13: =C12+C13 | D13: =D12+D13
A14: Net Profit (EBITDA) | B14: =B10-B14 | C14: =C10-C14 | D14: =D10-D14
A15: Net Margin % | B15: =B15/B9 | C15: =C15/C9 | D15: =D15/D9
A16: Break-even orders/mo | B16: =(B8/12)/(B5*(B6-B7)) | C16: =(C8/12)/(C5*(C6-C7)) | D16: =(D8/12)/(D5*(D6-D7))
A18: STARTUP CAPITAL REQUIRED
A19: Initial inventory (100 vials) | B19: 1900
A20: Website & branding | B20: 2500
A21: Legal / compliance setup | B21: 3500
A22: Cold-chain packaging (500 units) | B22: 1200
A23: Testing / COA setup | B23: 800
A24: Working capital (3 mo OpEx) | B24: 15000
A25: TOTAL STARTUP CAPITAL | B25: =SUM(B19:B24)
A27: VERDICT
A28: RENVOA CLINIC product pricing is PROFITABLE — 44–87% gross margins per SKU at wholesale MOQ.
A29: Base case Year 1 EBITDA ~$5K (3.5% net margin) after 25% marketing; break-even ~102 orders/month.
A30: Year 1 is tight — profitability improves sharply in Year 2 as marketing % drops and orders scale.
A31: Biggest risks: 100-vial inventory MOQ (~$1,900), cold-chain shipping, compliance, TB-500 thin margin.
